_csphi.pyd
spherepy/csphi.py
spherepy/file.py
spherepy/ops.py
spherepy/pkg_info.json
spherepy/plot_sphere.py
spherepy/pysphi.py
spherepy/sbessel.py
spherepy/spherepy.py
spherepy/verify.py
spherepy/__init__.py
spherepy/tests/test_spherepy.py
spherepy/tests/test_sphere_structures.py
spherepy/tests/test_sphi.py
spherepy-0.0.9.dist-info/DESCRIPTION.rst
spherepy-0.0.9.dist-info/METADATA
spherepy-0.0.9.dist-info/metadata.json
spherepy-0.0.9.dist-info/RECORD
spherepy-0.0.9.dist-info/top_level.txt
spherepy-0.0.9.dist-info/WHEEL
