Metadata-Version: 2.0
Name: spherepy
Version: 0.0.9
Summary: Numerical routines for working with spherical harmonic coefficients
Home-page: https://github.com/rdireen/spherepy
Author: Randy Direen
Author-email: spherepy@direentech.com
License: GPLv3
Download-URL: https://github.com/rdireen/spherepy/tarball/0.0.9
Keywords: sphere transform
Platform: UNKNOWN
Classifier: Development Status :: 3 - Alpha
Classifier: Intended Audience :: Education
Classifier: Intended Audience :: Science/Research
Classifier: License :: OSI Approved :: GNU General Public License v3 (GPLv3)
Classifier: Operating System :: Microsoft :: Windows :: Windows 7
Classifier: Operating System :: POSIX :: Linux
Classifier: Programming Language :: Python :: 2.7
Classifier: Programming Language :: Python :: 3.3
Classifier: Programming Language :: Python :: 3.4
Classifier: Programming Language :: Python :: Implementation :: CPython
Classifier: Topic :: Scientific/Engineering :: Mathematics
Requires-Dist: six
